fugue_jupyterlab/__init__.py
fugue_jupyterlab/_version.py
fugue_jupyterlab/labextension/build_log.json
fugue_jupyterlab/labextension/package.json
fugue_jupyterlab/labextension/schemas/fugue-jupyterlab/package.json.orig
fugue_jupyterlab/labextension/static/lib_index_js.3c2e8b99279308312cf8.js
fugue_jupyterlab/labextension/static/lib_index_js.3c2e8b99279308312cf8.js.map
fugue_jupyterlab/labextension/static/remoteEntry.32ee3cc4119500f7381b.js
fugue_jupyterlab/labextension/static/remoteEntry.32ee3cc4119500f7381b.js.map
fugue_jupyterlab/labextension/static/style.js
fugue_jupyterlab/labextension/static/style_index_js.b240bca48c0ab426068f.js
fugue_jupyterlab/labextension/static/style_index_js.b240bca48c0ab426068f.js.map
fugue_jupyterlab/labextension/static/vendors-node_modules_css-loader_dist_runtime_api_js-node_modules_css-loader_dist_runtime_cssW-72eba1.d4b9ac8d5de2bd348b84.js
fugue_jupyterlab/labextension/static/vendors-node_modules_css-loader_dist_runtime_api_js-node_modules_css-loader_dist_runtime_cssW-72eba1.d4b9ac8d5de2bd348b84.js.map
fugue_jupyterlab-0.0.1.data/data/share/jupyter/labextensions/fugue-jupyterlab/build_log.json
fugue_jupyterlab-0.0.1.data/data/share/jupyter/labextensions/fugue-jupyterlab/install.json
fugue_jupyterlab-0.0.1.data/data/share/jupyter/labextensions/fugue-jupyterlab/package.json
fugue_jupyterlab-0.0.1.data/data/share/jupyter/labextensions/fugue-jupyterlab/schemas/fugue-jupyterlab/package.json.orig
fugue_jupyterlab-0.0.1.data/data/share/jupyter/labextensions/fugue-jupyterlab/static/lib_index_js.3c2e8b99279308312cf8.js
fugue_jupyterlab-0.0.1.data/data/share/jupyter/labextensions/fugue-jupyterlab/static/lib_index_js.3c2e8b99279308312cf8.js.map
fugue_jupyterlab-0.0.1.data/data/share/jupyter/labextensions/fugue-jupyterlab/static/remoteEntry.32ee3cc4119500f7381b.js
fugue_jupyterlab-0.0.1.data/data/share/jupyter/labextensions/fugue-jupyterlab/static/remoteEntry.32ee3cc4119500f7381b.js.map
fugue_jupyterlab-0.0.1.dist-info/LICENSE
fugue_jupyterlab-0.0.1.dist-info/METADATA
fugue_jupyterlab-0.0.1.dist-info/WHEEL
fugue_jupyterlab-0.0.1.dist-info/top_level.txt
fugue_jupyterlab-0.0.1.dist-info/RECORD
